aliyunsdkmse/__init__.py
aliyunsdkmse/endpoint.py
aliyunsdkmse/request/__init__.py
aliyunsdkmse/request/v20190531/AddAuthPolicyRequest.py
aliyunsdkmse/request/v20190531/AddAuthResourceRequest.py
aliyunsdkmse/request/v20190531/AddBlackWhiteListRequest.py
aliyunsdkmse/request/v20190531/AddGatewayAuthConsumerRequest.py
aliyunsdkmse/request/v20190531/AddGatewayDomainRequest.py
aliyunsdkmse/request/v20190531/AddGatewayRequest.py
aliyunsdkmse/request/v20190531/AddGatewayRouteRequest.py
aliyunsdkmse/request/v20190531/AddGatewayServiceVersionRequest.py
aliyunsdkmse/request/v20190531/AddGatewaySlbRequest.py
aliyunsdkmse/request/v20190531/AddMigrationTaskRequest.py
aliyunsdkmse/request/v20190531/AddMockRuleRequest.py
aliyunsdkmse/request/v20190531/AddSSLCertRequest.py
aliyunsdkmse/request/v20190531/AddSecurityGroupRuleRequest.py
aliyunsdkmse/request/v20190531/AddServiceSourceRequest.py
aliyunsdkmse/request/v20190531/ApplyGatewayRouteRequest.py
aliyunsdkmse/request/v20190531/ApplyTagPoliciesRequest.py
aliyunsdkmse/request/v20190531/CloneNacosConfigRequest.py
aliyunsdkmse/request/v20190531/CreateApplicationRequest.py
aliyunsdkmse/request/v20190531/CreateCircuitBreakerRuleRequest.py
aliyunsdkmse/request/v20190531/CreateClusterRequest.py
aliyunsdkmse/request/v20190531/CreateEngineNamespaceRequest.py
aliyunsdkmse/request/v20190531/CreateFlowRuleRequest.py
aliyunsdkmse/request/v20190531/CreateMseServiceApplicationRequest.py
aliyunsdkmse/request/v20190531/CreateNacosConfigRequest.py
aliyunsdkmse/request/v20190531/CreateNacosInstanceRequest.py
aliyunsdkmse/request/v20190531/CreateNacosServiceRequest.py
aliyunsdkmse/request/v20190531/CreateOrUpdateSwimmingLaneGroupRequest.py
aliyunsdkmse/request/v20190531/CreateOrUpdateSwimmingLaneRequest.py
aliyunsdkmse/request/v20190531/CreateZnodeRequest.py
aliyunsdkmse/request/v20190531/DeleteAuthResourceRequest.py
aliyunsdkmse/request/v20190531/DeleteCircuitBreakerRulesRequest.py
aliyunsdkmse/request/v20190531/DeleteClusterRequest.py
aliyun_python_sdk_mse-3.0.24.dist-info/LICENSE
aliyun_python_sdk_mse-3.0.24.dist-info/METADATA
aliyun_python_sdk_mse-3.0.24.dist-info/WHEEL
aliyun_python_sdk_mse-3.0.24.dist-info/top_level.txt
aliyun_python_sdk_mse-3.0.24.dist-info/RECORD
